pulumiverse_matchbox/__init__.py
pulumiverse_matchbox/_utilities.py
pulumiverse_matchbox/group.py
pulumiverse_matchbox/profile.py
pulumiverse_matchbox/provider.py
pulumiverse_matchbox/pulumi-plugin.json
pulumiverse_matchbox/py.typed
pulumiverse_matchbox/config/__init__.py
pulumiverse_matchbox/config/__init__.pyi
pulumiverse_matchbox/config/vars.py
pulumiverse_matchbox-0.2.0.dist-info/METADATA
pulumiverse_matchbox-0.2.0.dist-info/WHEEL
pulumiverse_matchbox-0.2.0.dist-info/top_level.txt
pulumiverse_matchbox-0.2.0.dist-info/RECORD
