Metadata-Version: 2.1
Name: pulumiverse_matchbox
Version: 0.2.0
Summary: A Pulumi package for creating and managing the Matchbox iPXE server.
License: Apache-2.0
Project-URL: Homepage, https://www.pulumi.com
Project-URL: Repository, https://github.com/pulumiverse/pulumi-matchbox
Keywords: pulumi,matchbox,category/network
Requires-Python: >=3.8
Requires-Dist: parver >=0.2.1
Requires-Dist: pulumi <4.0.0,>=3.0.0
Requires-Dist: semver >=2.8.1
Requires-Dist: typing-extensions >=4.11 ; python_version < "3.11"
